ml_pipelines/__init__.py
ml_pipelines/cl_bases.py
ml_pipelines/cl_dataset.py
ml_pipelines/cl_project.py
ml_pipelines/client.py
ml_pipelines/deps.py
ml_pipelines/errors.py
ml_pipelines/mlp_api_pb2.py
ml_pipelines/mlp_api_pb2_grpc.py
ml_pipelines/vo_pb2.py
ml_pipelines/vo_pb2_grpc.py
ml_pipelines-1.0.23.dist-info/METADATA
ml_pipelines-1.0.23.dist-info/WHEEL
ml_pipelines-1.0.23.dist-info/top_level.txt
ml_pipelines-1.0.23.dist-info/RECORD
