Metadata-Version: 2.1
Name: ml-pipelines
Version: 1.0.23
Summary: Python client for ML Pipelines
Home-page: https://github.com/bitgn/ml-pipelines
Author: Rinat Abdullin
Author-email: rinat@abdullin.com
License: UNKNOWN
Platform: UNKNOWN
Classifier: Programming Language :: Python :: 3
Classifier: License :: OSI Approved :: BSD License
Classifier: Operating System :: OS Independent
Classifier: Development Status :: 3 - Alpha
Classifier: Topic :: Scientific/Engineering :: Information Analysis
Classifier: Topic :: Education
Requires-Dist: grpcio (>=1.12.0)
Requires-Dist: protobuf
